azureml/__init__.py
azureml/studio/__init__.py
azureml/studio/internal/Exceptions.xml
azureml/studio/internal/__init__.py
azureml/studio/internal/error.py
azureml/studio/internal/error_handler.py
azureml/studio/internal/module_telemetry.py
azureml/studio/internal/package_info.py
azureml/studio/internal/types.py
azureml/studio/internal/attributes/__init__.py
azureml/studio/internal/attributes/release_state.py
azureml/studio/internal/io/__init__.py
azureml/studio/internal/io/rwbuffer_manager.py
azureml/studio/internal/utils/__init__.py
azureml/studio/internal/utils/dependencies.py
azureml_designer_internal-0.0.78.dist-info/METADATA
azureml_designer_internal-0.0.78.dist-info/WHEEL
azureml_designer_internal-0.0.78.dist-info/top_level.txt
azureml_designer_internal-0.0.78.dist-info/RECORD
