Metadata-Version: 2.1
Name: azureml-designer-internal
Version: 0.0.78
Summary: Internal functionalities provided for Azure Machine Learning designer built-in modules. Not intended for public use.
Author: Microsoft Crop
Platform: any
Classifier: Programming Language :: Python :: 3
Classifier: License :: Other/Proprietary License
Classifier: Operating System :: OS Independent
Requires-Python: >=3.8
Requires-Dist: azureml-designer-core ==0.0.86
Requires-Dist: cffi ==1.15.1
Requires-Dist: msrest ==0.6.21
Requires-Dist: azureml-defaults ==1.60.0
Requires-Dist: Werkzeug ==3.0.6
Requires-Dist: azureml-telemetry ==1.60.0.*
Requires-Dist: azureml-pipeline-core ==1.60.0
